CRF/__init__.py
CRF-0.0.1a1.dist-info/LICENSE
CRF-0.0.1a1.dist-info/METADATA
CRF-0.0.1a1.dist-info/WHEEL
CRF-0.0.1a1.dist-info/top_level.txt
CRF-0.0.1a1.dist-info/RECORD
